filecheck/__init__.py
filecheck/__main__.py
filecheck/colors.py
filecheck/compiler.py
filecheck/error.py
filecheck/finput.py
filecheck/help.py
filecheck/logging.py
filecheck/main.py
filecheck/matcher.py
filecheck/ops.py
filecheck/options.py
filecheck/parser.py
filecheck/preprocess.py
filecheck/py.typed
filecheck/regex.py
filecheck-1.0.3.dist-info/LICENSE.txt
filecheck-1.0.3.dist-info/METADATA
filecheck-1.0.3.dist-info/WHEEL
filecheck-1.0.3.dist-info/entry_points.txt
filecheck-1.0.3.dist-info/RECORD
