Metadata-Version: 2.3
Name: filecheck
Version: 1.0.3
Summary: A Python-native clone of LLVMs FileCheck tool
License: Apache-2.0
Keywords: tests,filecheck,llvm
Author: Anton Lydike
Author-email: me@antonlydike.de
Requires-Python: >=3.10,<4.0
Classifier: License :: OSI Approved :: Apache Software License
Classifier: Programming Language :: Python :: 3
Classifier: Programming Language :: Python :: 3.10
Classifier: Programming Language :: Python :: 3.11
Classifier: Programming Language :: Python :: 3.12
Classifier: Programming Language :: Python :: 3.13
Project-URL: Homepage, https://github.com/AntonLydike/filecheck
Project-URL: Repository, https://github.com/AntonLydike/filecheck
